word_piece_tokenizer/BasicTokenizer.py
word_piece_tokenizer/Trie.py
word_piece_tokenizer/WordPieceTokenizer.py
word_piece_tokenizer/__init__.py
word_piece_tokenizer/utils.py
word_piece_tokenizer/vocab.txt
word_piece_tokenizer-1.0.1.dist-info/LICENSE.txt
word_piece_tokenizer-1.0.1.dist-info/METADATA
word_piece_tokenizer-1.0.1.dist-info/WHEEL
word_piece_tokenizer-1.0.1.dist-info/top_level.txt
word_piece_tokenizer-1.0.1.dist-info/RECORD
