Metadata-Version: 2.1
Name: word-piece-tokenizer
Version: 1.0.1
Summary: A Lightweight Word Piece Tokenizer
Author-email: Jing Hua <mail@dev.tjh.sg>
License: CC0 1.0 Universal
Project-URL: Repository, https://github.com/ztjhz/word-piece-tokenizer
Keywords: word,piece,tokenizer,transformer,bert,uncased,nlp,natural,language,processing
Classifier: License :: CC0 1.0 Universal (CC0 1.0) Public Domain Dedication
Classifier: Programming Language :: Python
Classifier: Programming Language :: Python :: 3
Requires-Python: >=3.9
License-File: LICENSE.txt
Provides-Extra: test
Requires-Dist: transformers ; extra == 'test'
